{
	"configurations" : 
	[
		{
			"directories" : 
			[
				{
					"build" : ".",
					"hasInstallRule" : true,
					"jsonFile" : "directory-.-Release-331648a4327976938ccc.json",
					"minimumCMakeVersion" : 
					{
						"string" : "3.12"
					},
					"projectIndex" : 0,
					"source" : ".",
					"targetIndexes" : 
					[
						0,
						1
					]
				}
			],
			"name" : "Release",
			"projects" : 
			[
				{
					"directoryIndexes" : 
					[
						0
					],
					"name" : "nav2_core",
					"targetIndexes" : 
					[
						0,
						1
					]
				}
			],
			"targets" : 
			[
				{
					"directoryIndex" : 0,
					"id" : "nav2_core_uninstall::@6890427a1f51a3e7e1df",
					"jsonFile" : "target-nav2_core_uninstall-Release-a9d724f4c77346fa0d55.json",
					"name" : "nav2_core_uninstall",
					"projectIndex" : 0
				},
				{
					"directoryIndex" : 0,
					"id" : "uninstall::@6890427a1f51a3e7e1df",
					"jsonFile" : "target-uninstall-Release-4ec11fec47be26902674.json",
					"name" : "uninstall",
					"projectIndex" : 0
				}
			]
		}
	],
	"kind" : "codemodel",
	"paths" : 
	{
		"build" : "/home/wheeltec/wheeltec_robot/build/nav2_core",
		"source" : "/home/wheeltec/wheeltec_robot/src/navigation2-humble/nav2_core"
	},
	"version" : 
	{
		"major" : 2,
		"minor" : 3
	}
}
